{
  "/_app": "pages/_app.js",
  "/_error": "pages/_error.js",
  "/change-password/[token]": "pages/change-password/[token].html",
  "/forgot-password": "pages/forgot-password.html",
  "/": "pages/index.html",
  "/login": "pages/login.html",
  "/project/[id]": "pages/project/[id].html",
  "/project/issue/[id]": "pages/project/issue/[id].html",
  "/project/report-issue": "pages/project/report-issue.html",
  "/register": "pages/register.html",
  "/_document": "pages/_document.js",
  "/404": "pages/404.html"
}